linkpreview/__init__.py
linkpreview/compose.py
linkpreview/exceptions.py
linkpreview/grabber.py
linkpreview/headers.py
linkpreview/helpers.py
linkpreview/link.py
linkpreview/linkpreview.py
linkpreview/preview/__init__.py
linkpreview/preview/base.py
linkpreview/preview/generic.py
linkpreview/preview/jsonld.py
linkpreview/preview/metabase.py
linkpreview/preview/microdata.py
linkpreview/preview/opengraph.py
linkpreview/preview/schemabase.py
linkpreview/preview/twittercard.py
tests/__init__.py
tests/helpers.py
tests/test_favicon.py
tests/test_generic.py
tests/test_grabber.py
tests/test_jsonld.py
tests/test_microdata.py
tests/test_opengraph.py
tests/test_preview.py
tests/test_soup.py
tests/test_twittercard.py
linkpreview-0.12.1.dist-info/LICENSE
linkpreview-0.12.1.dist-info/METADATA
linkpreview-0.12.1.dist-info/WHEEL
linkpreview-0.12.1.dist-info/top_level.txt
linkpreview-0.12.1.dist-info/RECORD
