Metadata-Version: 2.1
Name: linkpreview
Version: 0.12.1
Summary: Get link (URL) preview
Home-page: UNKNOWN
Author: MeyT
License: MIT
Keywords: link preview web htmlparse schema.org opengraph twittercard url
Platform: UNKNOWN
Classifier: Development Status :: 4 - Beta
Classifier: Intended Audience :: Developers
Classifier: License :: OSI Approved :: MIT License
Classifier: Operating System :: POSIX :: Linux
Classifier: Operating System :: Unix
Classifier: Programming Language :: Python :: 3.6
Classifier: Programming Language :: Python :: 3.7
Classifier: Programming Language :: Python :: 3.8
Classifier: Programming Language :: Python :: 3.9
Classifier: Programming Language :: Python :: 3.10
Classifier: Topic :: Software Development :: Libraries
